cosmic/__init__.py
cosmic/batch.py
cosmic/chunker.py
cosmic/cli.py
cosmic/exceptions.py
cosmic/core/__init__.py
cosmic/core/chunk.py
cosmic/core/config.py
cosmic/core/document.py
cosmic/core/enums.py
cosmic/fallback/__init__.py
cosmic/fallback/fixed_length.py
cosmic/fallback/semantic_only.py
cosmic/fallback/sliding_window.py
cosmic/models/__init__.py
cosmic/models/coreference.py
cosmic/models/domain_classifier.py
cosmic/models/embeddings.py
cosmic/models/llm.py
cosmic/models/ollama.py
cosmic/pipeline/__init__.py
cosmic/pipeline/base.py
cosmic/pipeline/domain.py
cosmic/pipeline/fusion.py
cosmic/pipeline/reference.py
cosmic/pipeline/semantic.py
cosmic/pipeline/structure.py
cosmic/pipeline/verification.py
cosmic/scoring/__init__.py
cosmic/scoring/clustering.py
cosmic/scoring/dcs.py
cosmic/utils/__init__.py
cosmic/utils/patterns.py
cosmic/utils/tokenizer.py
cosmic_chunker-1.1.0.dist-info/licenses/LICENSE
cosmic_chunker-1.1.0.dist-info/METADATA
cosmic_chunker-1.1.0.dist-info/WHEEL
cosmic_chunker-1.1.0.dist-info/entry_points.txt
cosmic_chunker-1.1.0.dist-info/top_level.txt
cosmic_chunker-1.1.0.dist-info/RECORD
