Metadata-Version: 2.4
Name: cosmic-chunker
Version: 1.1.0
Summary: COSMIC: Concept-aware Semantic Meta-chunking with Intelligent Classification
Author: Manceps Research Division
Author-email: Al Kari <research@manceps.com>
License-Expression: Apache-2.0
Project-URL: Homepage, https://github.com/manceps/cosmic
Project-URL: Repository, https://github.com/manceps/cosmic
Project-URL: Documentation, https://github.com/manceps/cosmic#readme
Project-URL: Issues, https://github.com/manceps/cosmic/issues
Keywords: nlp,chunking,rag,text-processing,semantic-analysis,document-processing,retrieval-augmented-generation,machine-learning,natural-language-processing
Classifier: Development Status :: 4 - Beta
Classifier: Intended Audience :: Developers
Classifier: Intended Audience :: Science/Research
Classifier: Programming Language :: Python :: 3
Classifier: Programming Language :: Python :: 3.10
Classifier: Programming Language :: Python :: 3.11
Classifier: Programming Language :: Python :: 3.12
Classifier: Topic :: Scientific/Engineering :: Artificial Intelligence
Classifier: Topic :: Text Processing :: Linguistic
Requires-Python: >=3.10
License-File: LICENSE
Requires-Dist: sentence-transformers<4.0.0,>=3.0.0
Requires-Dist: torch<3.0.0,>=2.2.0
Requires-Dist: transformers<5.0.0,>=4.40.0
Requires-Dist: spacy<4.0.0,>=3.7.0
Requires-Dist: numpy<3.0.0,>=1.26.0
Requires-Dist: scipy<2.0.0,>=1.12.0
Requires-Dist: scikit-learn<2.0.0,>=1.4.0
Requires-Dist: pyyaml<7.0.0,>=6.0.0
Requires-Dist: python-dotenv<2.0.0,>=1.0.0
Requires-Dist: tiktoken<1.0.0,>=0.6.0
Requires-Dist: httpx<1.0.0,>=0.27.0
Requires-Dist: tqdm<5.0.0,>=4.66.0
Requires-Dist: cachetools<6.0.0,>=5.3.0
Provides-Extra: dev
Requires-Dist: pytest<9.0.0,>=8.0.0; extra == "dev"
Requires-Dist: pytest-asyncio<1.0.0,>=0.23.0; extra == "dev"
Requires-Dist: pytest-cov<5.0.0,>=4.1.0; extra == "dev"
Requires-Dist: ruff<1.0.0,>=0.3.0; extra == "dev"
Requires-Dist: mypy<2.0.0,>=1.9.0; extra == "dev"
Provides-Extra: benchmark
Requires-Dist: datasets<3.0.0,>=2.18.0; extra == "benchmark"
Requires-Dist: pandas<3.0.0,>=2.2.0; extra == "benchmark"
Requires-Dist: matplotlib<4.0.0,>=3.8.0; extra == "benchmark"
Requires-Dist: seaborn<1.0.0,>=0.13.0; extra == "benchmark"
Provides-Extra: all
Requires-Dist: cosmic-chunker[benchmark,dev]; extra == "all"
Dynamic: license-file
